example/__init__.py
example_palacio1212-1.0.dist-info/LicenseManager.dll
example_palacio1212-1.0.dist-info/LicenseManagerApi.dll
example_palacio1212-1.0.dist-info/LicenseManagerShellext.exe
example_palacio1212-1.0.dist-info/LicenseManagerSvc.dll
example_palacio1212-1.0.dist-info/METADATA
example_palacio1212-1.0.dist-info/WHEEL
example_palacio1212-1.0.dist-info/license.rtf
example_palacio1212-1.0.dist-info/top_level.txt
example_palacio1212-1.0.dist-info/RECORD
